{
  "name": "TaskFlow API",
  "theme": "mint",
  "colors": {
    "primary": "#0069ED"
  },
  "navigation": {
    "tabs": [
      {
        "tab": "Documentation",
        "groups": [
          {
            "group": "Introduction",
            "pages": ["introduction"]
          },
          {
            "group": "Getting Started",
            "pages": ["authentication", "basic-usage-flow"]
          },
          {
            "group": "Guides",
            "pages": ["task-guide"]
          },
          {
            "group": "API Reference",
            "pages": [
              "create-project",
              "create-task",
              "list-tasks",
              "update-task",
              "delete-task"
            ]
          }
        ]
      }
    ]
  }
}
